acrcloud/__init__.py
acrcloud/acrcloud_extr_tool.so
acrcloud/recognizer.py
pyacrcloud_patch-1.0.1.dist-info/METADATA
pyacrcloud_patch-1.0.1.dist-info/WHEEL
pyacrcloud_patch-1.0.1.dist-info/top_level.txt
pyacrcloud_patch-1.0.1.dist-info/RECORD
